[
  {
    "original": "http://ada.ky.gov/ADAEMPLOYMENTTaxIncentives.ppt",
    "mimetype": "vnd.ms-powerpoint",
    "title": "Human Development Institute Promoting Independence, Productivity, and Integration for All People _________________________________",
    "company": "-",
    "creation_date": "1998-12-17T14:31:23Z",
    "last_modified": "2005-03-25T15:56:39Z",
    "revision_number": 47,
    "slide_count": 31,
    "word_count": 781,
    "file_size": 137216,
    "file_name": "4Y6Z6KRRHS3TIVQ2ZJVYVW7RSGXOBS6Y.ppt"
  },
  {
    "original": "http://astrophysics.gsfc.nasa.gov/conferences/supernova1987a/Staveley-Smith.ppt",
    "mimetype": "vnd.ms-powerpoint",
    "title": "xNTD and the Pathway to SKA",
    "company": "Lister Staveley-Smith",
    "creation_date": "-",
    "last_modified": "2007-02-20T13:41:45Z",
    "revision_number": 51,
    "slide_count": 17,
    "word_count": 553,
    "file_size": 1580032,
    "file_name": "7EZSHVTKZE2FXP5SXI6DO2RJPIDLMXOP.ppt"
  },
  {
    "original": "http://www.awm.delaware.gov/SiteCollectionDocuments/AWM%20Gallery/VSM%20Data%20Metrics.ppt",
    "mimetype": "vnd.ms-powerpoint",
    "title": "VSM Data Metrics",
    "company": "State of Delaware",
    "creation_date": "2006-10-16T16:19:52Z",
    "last_modified": "2006-10-26T19:37:20Z",
    "revision_number": 4,
    "slide_count": 1,
    "word_count": 2,
    "file_size": 136704,
    "file_name": "ZHT4MJOX7D7OIRMCBPX4PMWZ4OQ7XSZ2.ppt"
  },
  {
    "original": "http://www.bcbintranet.sc.gov/OHR/hr-advisory/WorkforcePlanningImportant.ppt",
    "mimetype": "vnd.ms-powerpoint",
    "title": "Why Workforce Planning is Important during Hard times",
    "company": "SC Office of Human Resources",
    "creation_date": "2009-01-07T14:28:04Z",
    "last_modified": "2009-01-09T16:31:58Z",
    "revision_number": 7,
    "slide_count": 9,
    "word_count": 238,
    "file_size": 53760,
    "file_name": "KDBPF6PJCBK2BEIYC2L5I33THZMINFML.ppt"
  },
  {
    "original": "http://beamdocs.fnal.gov/AD/DocDB/0010/001026/003/040225_Lehman_Review.ppt",
    "mimetype": "vnd.ms-powerpoint",
    "title": "PowerPoint Presentation",
    "company": "Fermilab PPD",
    "creation_date": "2003-06-30T15:15:33Z",
    "last_modified": "2004-02-22T22:33:55Z",
    "revision_number": 122,
    "slide_count": 45,
    "word_count": 1638,
    "file_size": 8227840,
    "file_name": "OJOHGFEE4EI44UNSXLNV4Q5IKJ2L4H2Y.ppt"
  }
]